bayeso/__init__.py
bayeso/acquisition.py
bayeso/constants.py
bayeso/covariance.py
bayeso/thompson_sampling.py
bayeso/bo/__init__.py
bayeso/bo/base_bo.py
bayeso/bo/bo_w_gp.py
bayeso/bo/bo_w_tp.py
bayeso/bo/bo_w_trees.py
bayeso/gp/__init__.py
bayeso/gp/gp.py
bayeso/gp/gp_kernel.py
bayeso/gp/gp_likelihood.py
bayeso/tp/__init__.py
bayeso/tp/tp.py
bayeso/tp/tp_kernel.py
bayeso/tp/tp_likelihood.py
bayeso/trees/__init__.py
bayeso/trees/trees_common.py
bayeso/trees/trees_generic_trees.py
bayeso/trees/trees_random_forest.py
bayeso/utils/__init__.py
bayeso/utils/utils_bo.py
bayeso/utils/utils_common.py
bayeso/utils/utils_covariance.py
bayeso/utils/utils_gp.py
bayeso/utils/utils_logger.py
bayeso/utils/utils_plotting.py
bayeso/wrappers/__init__.py
bayeso/wrappers/wrappers_bo_class.py
bayeso/wrappers/wrappers_bo_function.py
bayeso-0.6.0.dist-info/LICENSE
bayeso-0.6.0.dist-info/METADATA
bayeso-0.6.0.dist-info/WHEEL
bayeso-0.6.0.dist-info/top_level.txt
bayeso-0.6.0.dist-info/RECORD
