Metadata-Version: 2.1
Name: bayeso
Version: 0.6.0
Summary: Simple, but essential Bayesian optimization package
Author-email: Jungtaek Kim <jungtaek.kim.mail@gmail.com>
License: MIT
Project-URL: Homepage, https://bayeso.org
Project-URL: Source, https://github.com/jungtaekkim/bayeso
Project-URL: Issues, https://github.com/jungtaekkim/bayeso/issues
Classifier: Programming Language :: Python :: 3
Classifier: Intended Audience :: Science/Research
Classifier: License :: OSI Approved :: MIT License
Classifier: Operating System :: OS Independent
Classifier: Topic :: Scientific/Engineering
Classifier: Topic :: Scientific/Engineering :: Artificial Intelligence
Requires-Python: >=3.7
License-File: LICENSE
Requires-Dist: numpy
Requires-Dist: scipy
Requires-Dist: cma
Requires-Dist: tqdm
Provides-Extra: dev
Requires-Dist: pytest ; extra == 'dev'
Requires-Dist: pytest-benchmark ; extra == 'dev'
Requires-Dist: pytest-timeout ; extra == 'dev'
Requires-Dist: pytest-cov ; extra == 'dev'
Requires-Dist: coveralls ; extra == 'dev'
Requires-Dist: sphinx ; extra == 'dev'
Requires-Dist: sphinx-rtd-theme ; extra == 'dev'
Requires-Dist: jupyter ; extra == 'dev'
Requires-Dist: jupytext ; extra == 'dev'
Requires-Dist: pylint ; extra == 'dev'
Requires-Dist: wheel ; extra == 'dev'
Requires-Dist: build ; extra == 'dev'
Requires-Dist: twine ; extra == 'dev'
Provides-Extra: examples
Requires-Dist: xgboost ; extra == 'examples'
Requires-Dist: scikit-learn ; extra == 'examples'
Provides-Extra: optional
Requires-Dist: scipydirect ; extra == 'optional'
Requires-Dist: matplotlib ; extra == 'optional'
Requires-Dist: bayeso-benchmarks ; extra == 'optional'
